{
    "cli": {
        "version": ">= 12.0.0"
    },
    "build": {
        "development": {
            "developmentClient": true,
            "distribution": "internal",
            "env": {}
        },
        "preview": {
            "distribution": "internal",
            "android": {
                "buildType": "apk"
            },
            "env": {
                "EXPO_PUBLIC_MISTRAL_API_KEY": "LNsrHZVDZ62LTqabSfmI3Mp3DFGyAGQj"
            }
        },
        "production": {
            "env": {
                "EXPO_PUBLIC_MISTRAL_API_KEY": "LNsrHZVDZ62LTqabSfmI3Mp3DFGyAGQj"
            }
        }
    },
    "submit": {
        "production": {}
    }
}